facturapdf-0.0.4.dist-info/DESCRIPTION.rst
facturapdf-0.0.4.dist-info/WHEEL
facturapdf-0.0.4.dist-info/top_level.txt
facturapdf-0.0.4.dist-info/RECORD
facturapdf-0.0.4.dist-info/METADATA
facturapdf-0.0.4.dist-info/metadata.json
facturapdf/generators.py
facturapdf/templates.py
facturapdf/dtos.py
facturapdf/styles.py
facturapdf/helper.py
facturapdf/strategies.py
facturapdf/__about__.py
facturapdf/flowables.py
facturapdf/story_builders.py
facturapdf/__init__.py
