Metadata-Version: 2.0
Name: facturapdf
Version: 0.0.4
Summary: Create PDF invoice according to Spanish regulations.
Home-page: https://github.com/initios/factura-pdf
Author: Carlos Goce
Author-email: cgonzalez@initios.com
License: BSD 3-Clause License
Platform: UNKNOWN
Classifier: Programming Language :: Python
Classifier: Programming Language :: Python :: 2.7
Classifier: Programming Language :: Python :: 3.4
Classifier: Development Status :: 3 - Alpha
Classifier: License :: OSI Approved :: BSD License
Requires-Dist: reportlab (==3.1.44)
